pybitable
