Metadata-Version: 2.1
Name: pybitable
Version: 0.1.1
Summary: A Python wrapper around Lark bitable to sql.
Home-page: https://github.com/lloydzhou/pybitable
Author: lloydzhou
Author-email: lloydzhou@qq.com
License: UNKNOWN
Platform: UNKNOWN
Requires-Python: >=3.10
Provides-Extra: cli
Provides-Extra: sqlalchemy
